{
  "SPDXID" : "SPDXRef-DOCUMENT",
  "spdxVersion" : "SPDX-2.3",
  "creationInfo" : {
    "comment" : "Converted from CycloneDX spec version 1.4",
    "created" : "2023-10-07T08:19:33Z",
    "creators" : [ "Tool: CycloneDX:cyclonedx-bom-3.11.2", "Tool: CycloneDX:cyclonedx-python-lib-3.1.5", "Tool: CycloneToSpdx-0.1.4" ],
    "licenseListVersion" : "3.22"
  },
  "name" : "From-Cyclone-DX",
  "dataLicense" : "CC0-1.0",
  "annotations" : [ {
    "annotationDate" : "2023-10-07T08:19:35Z",
    "annotationType" : "OTHER",
    "annotator" : "Tool: CycloneToSpdx",
    "comment" : "MISSING_CDX_PROPERTY:extensions={}"
  } ],
  "documentNamespace" : "https://cyclonedx/36a8beb3-6ccd-4711-a82b-0ca180370496_1",
  "packages" : [ {
    "SPDXID" : "SPDXRef-b05ba607-faf7-4273-961d-de89a4ad17ed",
    "annotations" : [ {
      "annotationDate" : "2023-10-07T08:19:35Z",
      "annotationType" : "OTHER",
      "annotator" : "Tool: CycloneToSpdx",
      "comment" : "MISSING_CDX_PROPERTY:componentType=\"LIBRARY\""
    } ],
    "copyrightText" : "NOASSERTION",
    "downloadLocation" : "NOASSERTION",
    "externalRefs" : [ {
      "referenceCategory" : "PACKAGE-MANAGER",
      "referenceLocator" : "pkg:pypi/jmespath@1.0.1",
      "referenceType" : "purl"
    } ],
    "filesAnalyzed" : false,
    "licenseConcluded" : "NOASSERTION",
    "licenseDeclared" : "NOASSERTION",
    "name" : "jmespath",
    "primaryPackagePurpose" : "LIBRARY",
    "versionInfo" : "1.0.1"
  }, {
    "SPDXID" : "SPDXRef-8d038473-f450-4e8f-a104-ef1fead5b400",
    "annotations" : [ {
      "annotationDate" : "2023-10-07T08:19:35Z",
      "annotationType" : "OTHER",
      "annotator" : "Tool: CycloneToSpdx",
      "comment" : "MISSING_CDX_PROPERTY:componentType=\"LIBRARY\""
    } ],
    "copyrightText" : "NOASSERTION",
    "downloadLocation" : "NOASSERTION",
    "externalRefs" : [ {
      "referenceCategory" : "PACKAGE-MANAGER",
      "referenceLocator" : "pkg:pypi/scooby@0.7.4",
      "referenceType" : "purl"
    } ],
    "filesAnalyzed" : false,
    "licenseConcluded" : "NOASSERTION",
    "licenseDeclared" : "NOASSERTION",
    "name" : "scooby",
    "primaryPackagePurpose" : "LIBRARY",
    "versionInfo" : "0.7.4"
  }, {
    "SPDXID" : "SPDXRef-db5c9259-c289-46a2-ae7b-e5560031fabd",
    "annotations" : [ {
      "annotationDate" : "2023-10-07T08:19:35Z",
      "annotationType" : "OTHER",
      "annotator" : "Tool: CycloneToSpdx",
      "comment" : "MISSING_CDX_PROPERTY:componentType=\"LIBRARY\""
    } ],
    "copyrightText" : "NOASSERTION",
    "downloadLocation" : "NOASSERTION",
    "externalRefs" : [ {
      "referenceCategory" : "PACKAGE-MANAGER",
      "referenceLocator" : "pkg:pypi/requests-cache@1.1.0",
      "referenceType" : "purl"
    } ],
    "filesAnalyzed" : false,
    "licenseConcluded" : "NOASSERTION",
    "licenseDeclared" : "NOASSERTION",
    "name" : "requests-cache",
    "primaryPackagePurpose" : "LIBRARY",
    "versionInfo" : "1.1.0"
  }, {
    "SPDXID" : "SPDXRef-8c3e8e0f-1aa6-4da3-badd-f84afaf311b2",
    "annotations" : [ {
      "annotationDate" : "2023-10-07T08:19:35Z",
      "annotationType" : "OTHER",
      "annotator" : "Tool: CycloneToSpdx",
      "comment" : "MISSING_CDX_PROPERTY:componentType=\"LIBRARY\""
    } ],
    "copyrightText" : "NOASSERTION",
    "downloadLocation" : "NOASSERTION",
    "externalRefs" : [ {
      "referenceCategory" : "PACKAGE-MANAGER",
      "referenceLocator" : "pkg:pypi/cogapp@3.3.0",
      "referenceType" : "purl"
    } ],
    "filesAnalyzed" : false,
    "licenseConcluded" : "NOASSERTION",
    "licenseDeclared" : "NOASSERTION",
    "name" : "cogapp",
    "primaryPackagePurpose" : "LIBRARY",
    "versionInfo" : "3.3.0"
  }, {
    "SPDXID" : "SPDXRef-1a442806-2c3b-46fd-ae9d-65efc0bd550d",
    "annotations" : [ {
      "annotationDate" : "2023-10-07T08:19:35Z",
      "annotationType" : "OTHER",
      "annotator" : "Tool: CycloneToSpdx",
      "comment" : "MISSING_CDX_PROPERTY:componentType=\"LIBRARY\""
    } ],
    "copyrightText" : "NOASSERTION",
    "downloadLocation" : "NOASSERTION",
    "externalRefs" : [ {
      "referenceCategory" : "PACKAGE-MANAGER",
      "referenceLocator" : "pkg:pypi/pydantic@2.4.2",
      "referenceType" : "purl"
    } ],
    "filesAnalyzed" : false,
    "licenseConcluded" : "NOASSERTION",
    "licenseDeclared" : "NOASSERTION",
    "name" : "pydantic",
    "primaryPackagePurpose" : "LIBRARY",
    "versionInfo" : "2.4.2"
  }, {
    "SPDXID" : "SPDXRef-f694e3fa-ff36-4bce-8ef8-1da9c57e7243",
    "annotations" : [ {
      "annotationDate" : "2023-10-07T08:19:35Z",
      "annotationType" : "OTHER",
      "annotator" : "Tool: CycloneToSpdx",
      "comment" : "MISSING_CDX_PROPERTY:componentType=\"LIBRARY\""
    } ],
    "copyrightText" : "NOASSERTION",
    "downloadLocation" : "NOASSERTION",
    "externalRefs" : [ {
      "referenceCategory" : "PACKAGE-MANAGER",
      "referenceLocator" : "pkg:pypi/typer@0.9.0",
      "referenceType" : "purl"
    } ],
    "filesAnalyzed" : false,
    "licenseConcluded" : "NOASSERTION",
    "licenseDeclared" : "NOASSERTION",
    "name" : "typer",
    "primaryPackagePurpose" : "LIBRARY",
    "versionInfo" : "0.9.0"
  }, {
    "SPDXID" : "SPDXRef-1355010a-c15c-4c47-84d0-1370129ae4c3",
    "annotations" : [ {
      "annotationDate" : "2023-10-07T08:19:35Z",
      "annotationType" : "OTHER",
      "annotator" : "Tool: CycloneToSpdx",
      "comment" : "MISSING_CDX_PROPERTY:componentType=\"LIBRARY\""
    } ],
    "copyrightText" : "NOASSERTION",
    "downloadLocation" : "NOASSERTION",
    "externalRefs" : [ {
      "referenceCategory" : "PACKAGE-MANAGER",
      "referenceLocator" : "pkg:pypi/atlassian-python-api@3.41.2",
      "referenceType" : "purl"
    } ],
    "filesAnalyzed" : false,
    "licenseConcluded" : "NOASSERTION",
    "licenseDeclared" : "NOASSERTION",
    "name" : "atlassian-python-api",
    "primaryPackagePurpose" : "LIBRARY",
    "versionInfo" : "3.41.2"
  } ],
  "relationships" : [ {
    "spdxElementId" : "SPDXRef-DOCUMENT",
    "relationshipType" : "DESCRIBES",
    "relatedSpdxElement" : "SPDXRef-1a442806-2c3b-46fd-ae9d-65efc0bd550d"
  }, {
    "spdxElementId" : "SPDXRef-DOCUMENT",
    "relationshipType" : "DESCRIBES",
    "relatedSpdxElement" : "SPDXRef-b05ba607-faf7-4273-961d-de89a4ad17ed"
  }, {
    "spdxElementId" : "SPDXRef-DOCUMENT",
    "relationshipType" : "DESCRIBES",
    "relatedSpdxElement" : "SPDXRef-db5c9259-c289-46a2-ae7b-e5560031fabd"
  }, {
    "spdxElementId" : "SPDXRef-DOCUMENT",
    "relationshipType" : "DESCRIBES",
    "relatedSpdxElement" : "SPDXRef-8c3e8e0f-1aa6-4da3-badd-f84afaf311b2"
  }, {
    "spdxElementId" : "SPDXRef-DOCUMENT",
    "relationshipType" : "DESCRIBES",
    "relatedSpdxElement" : "SPDXRef-1355010a-c15c-4c47-84d0-1370129ae4c3"
  }, {
    "spdxElementId" : "SPDXRef-DOCUMENT",
    "relationshipType" : "DESCRIBES",
    "relatedSpdxElement" : "SPDXRef-f694e3fa-ff36-4bce-8ef8-1da9c57e7243"
  }, {
    "spdxElementId" : "SPDXRef-DOCUMENT",
    "relationshipType" : "DESCRIBES",
    "relatedSpdxElement" : "SPDXRef-8d038473-f450-4e8f-a104-ef1fead5b400"
  } ]
}